LICENSE
README.md
cli.py
core/__init__.py
core/reading.py
code_zipper-0.1.3.dist-info/METADATA
code_zipper-0.1.3.dist-info/WHEEL
code_zipper-0.1.3.dist-info/entry_points.txt
code_zipper-0.1.3.dist-info/licenses/LICENSE
code_zipper-0.1.3.dist-info/RECORD
